.gitignore
CHANGES.txt
CONTRIBUTORS.txt
COPYRIGHT.txt
LICENSE.txt
README.md
setup.py
superslacker/__init__.py
superslacker/superslacker.py
superslacker.egg-info/PKG-INFO
superslacker.egg-info/SOURCES.txt
superslacker.egg-info/dependency_links.txt
superslacker.egg-info/entry_points.txt
superslacker.egg-info/not-zip-safe
superslacker.egg-info/requires.txt
superslacker.egg-info/top_level.txt
superslacker/tests/__init__.py
superslacker/tests/superslacker_test.py