Metadata-Version: 2.1
Name: superslacker
Version: 0.9.1
Summary: superslacker plugin for supervisord
Home-page: https://github.com/MTSolutions/superslacker
Author: Sebastian Lara Menares
Author-email: slaramen@gmail.com
Maintainer: Sebastian Lara Menares
Maintainer-email: slaramen@gmail.com
License: BSD-derived (http://www.repoze.org/LICENSE.txt)
Keywords: supervisor slack monitoring
Platform: UNKNOWN
Classifier: Development Status :: 3 - Alpha
Classifier: Environment :: No Input/Output (Daemon)
Classifier: Intended Audience :: System Administrators
Classifier: Natural Language :: English
Classifier: Operating System :: POSIX
Classifier: Programming Language :: Python :: 2
Classifier: Programming Language :: Python :: 2.6
Classifier: Programming Language :: Python :: 2.7
Classifier: Programming Language :: Python :: 3
Classifier: Programming Language :: Python :: 3.2
Classifier: Programming Language :: Python :: 3.3
Classifier: Programming Language :: Python :: 3.4
Classifier: Topic :: System :: Boot
Classifier: Topic :: System :: Monitoring
Classifier: Topic :: System :: Systems Administration
License-File: LICENSE.txt
